getprotocol/__init__.py
getprotocol/getprotocol.py
getprotocol-0.2.dist-info/LICENSE
getprotocol-0.2.dist-info/METADATA
getprotocol-0.2.dist-info/WHEEL
getprotocol-0.2.dist-info/entry_points.txt
getprotocol-0.2.dist-info/top_level.txt
getprotocol-0.2.dist-info/RECORD
