Metadata-Version: 2.1
Name: getprotocol
Version: 0.2
Summary: Simple script to get if host is using http or https.
Home-page: https://github.com/Anon-Exploiter/getprotocol
Author: Syed Umar Arfeen
Author-email: 18597330+Anon-Exploiter@users.noreply.github.com
License: MIT
Platform: UNKNOWN
Requires-Dist: requests
